{
  "manifestVersion": "3.2",
  "proxies": [
    {
      "address": "0x3b0c224538e323616Ba25344E3eDF81c9B71f014",
      "txHash": "0x40c1f28099ec37de3c07ac1d3191db4f19919ee582724ad06fa94009043639ba",
      "kind": "uups"
    }
  ],
  "impls": {
    "790cfaae7885a843185839b8b9938097dd7ba628db142b1c33924cca5eb3a43a": {
      "address": "0x139072bEbfF70bD0fa38251aE6f6827c075CeFDD",
      "txHash": "0xaafc850d6bdf5baf8f47fdae54c0923bfee373279b3013a9b5513aa8a7749321",
      "layout": {
        "storage": [
          {
            "contract": "Initializable",
            "label": "_initialized",
            "type": "t_uint8",
            "src": "../@openzeppelin/contracts-upgradeable/proxy/utils/Initializable.sol:62",
            "retypedFrom": "bool"
          },
          {
            "contract": "Initializable",
            "label": "_initializing",
            "type": "t_bool",
            "src": "../@openzeppelin/contracts-upgradeable/proxy/utils/Initializable.sol:67"
          },
          {
            "contract": "ContextUpgradeable",
            "label": "__gap",
            "type": "t_array(t_uint256)50_storage",
            "src": "../@openzeppelin/contracts-upgradeable/utils/ContextUpgradeable.sol:36"
          },
          {
            "contract": "ERC20Upgradeable",
            "label": "_balances",
            "type": "t_mapping(t_address,t_uint256)",
            "src": "../@openzeppelin/contracts-upgradeable/token/ERC20/ERC20Upgradeable.sol:37"
          },
          {
            "contract": "ERC20Upgradeable",
            "label": "_allowances",
            "type": "t_mapping(t_address,t_mapping(t_address,t_uint256))",
            "src": "../@openzeppelin/contracts-upgradeable/token/ERC20/ERC20Upgradeable.sol:39"
          },
          {
            "contract": "ERC20Upgradeable",
            "label": "_totalSupply",
            "type": "t_uint256",
            "src": "../@openzeppelin/contracts-upgradeable/token/ERC20/ERC20Upgradeable.sol:41"
          },
          {
            "contract": "ERC20Upgradeable",
            "label": "_name",
            "type": "t_string_storage",
            "src": "../@openzeppelin/contracts-upgradeable/token/ERC20/ERC20Upgradeable.sol:43"
          },
          {
            "contract": "ERC20Upgradeable",
            "label": "_symbol",
            "type": "t_string_storage",
            "src": "../@openzeppelin/contracts-upgradeable/token/ERC20/ERC20Upgradeable.sol:44"
          },
          {
            "contract": "ERC20Upgradeable",
            "label": "__gap",
            "type": "t_array(t_uint256)45_storage",
            "src": "../@openzeppelin/contracts-upgradeable/token/ERC20/ERC20Upgradeable.sol:394"
          },
          {
            "contract": "OwnableUpgradeable",
            "label": "_owner",
            "type": "t_address",
            "src": "../@openzeppelin/contracts-upgradeable/access/OwnableUpgradeable.sol:22"
          },
          {
            "contract": "OwnableUpgradeable",
            "label": "__gap",
            "type": "t_array(t_uint256)49_storage",
            "src": "../@openzeppelin/contracts-upgradeable/access/OwnableUpgradeable.sol:94"
          },
          {
            "contract": "ERC20BurnableUpgradeable",
            "label": "__gap",
            "type": "t_array(t_uint256)50_storage",
            "src": "../@openzeppelin/contracts-upgradeable/token/ERC20/extensions/ERC20BurnableUpgradeable.sol:51"
          },
          {
            "contract": "PausableUpgradeable",
            "label": "_paused",
            "type": "t_bool",
            "src": "../@openzeppelin/contracts-upgradeable/security/PausableUpgradeable.sol:29"
          },
          {
            "contract": "PausableUpgradeable",
            "label": "__gap",
            "type": "t_array(t_uint256)49_storage",
            "src": "../@openzeppelin/contracts-upgradeable/security/PausableUpgradeable.sol:116"
          },
          {
            "contract": "ERC1967UpgradeUpgradeable",
            "label": "__gap",
            "type": "t_array(t_uint256)50_storage",
            "src": "../@openzeppelin/contracts-upgradeable/proxy/ERC1967/ERC1967UpgradeUpgradeable.sol:211"
          },
          {
            "contract": "UUPSUpgradeable",
            "label": "__gap",
            "type": "t_array(t_uint256)50_storage",
            "src": "../@openzeppelin/contracts-upgradeable/proxy/utils/UUPSUpgradeable.sol:107"
          }
        ],
        "types": {
          "t_array(t_uint256)50_storage": {
            "label": "uint256[50]"
          },
          "t_uint256": {
            "label": "uint256"
          },
          "t_bool": {
            "label": "bool"
          },
          "t_array(t_uint256)49_storage": {
            "label": "uint256[49]"
          },
          "t_address": {
            "label": "address"
          },
          "t_mapping(t_address,t_uint256)": {
            "label": "mapping(address => uint256)"
          },
          "t_mapping(t_address,t_mapping(t_address,t_uint256))": {
            "label": "mapping(address => mapping(address => uint256))"
          },
          "t_string_storage": {
            "label": "string"
          },
          "t_array(t_uint256)45_storage": {
            "label": "uint256[45]"
          },
          "t_uint8": {
            "label": "uint8"
          }
        }
      }
    }
  }
}
